pyc3l/ApiCommunication.py
pyc3l/ApiHandling.py
pyc3l/CryptoAsim.py
pyc3l/__init__.py
pyc3l/common.py
pyc3l/pcache.py
pyc3l/store.py
pyc3l/wallet.py
pyc3l/lib/__init__.py
pyc3l/lib/dt.py
pyc3l-0.6.0.dist-info/METADATA
pyc3l-0.6.0.dist-info/WHEEL
pyc3l-0.6.0.dist-info/licenses/LICENSE
pyc3l-0.6.0.dist-info/RECORD
