Metadata-Version: 2.4
Name: pyc3l
Version: 0.6.0
Summary: ComChain API client library
Project-URL: Homepage, https://github.com/com-chain/pyc3l
Project-URL: Bug Tracker, https://github.com/com-chain/pyc3l/issues
Author-email: Florian Dubath <florian@dubath.org>
License-File: LICENSE
Classifier: License :: OSI Approved :: MIT License
Classifier: Operating System :: OS Independent
Classifier: Programming Language :: Python :: 3
Requires-Python: >=3.7
Requires-Dist: ecdsa
Requires-Dist: eth-account==0.5.9
Requires-Dist: hatch[test]
Requires-Dist: kids-cache
Requires-Dist: minimock[test]
Requires-Dist: requests
Requires-Dist: setuptools; python_version >= '3.12'
Requires-Dist: web3
